notificationz_sdk_python/__init__.py
notificationz_sdk_python/models.py
notificationz_sdk_python/notification.py
notificationz_sdk_python-0.5.0.dist-info/WHEEL
notificationz_sdk_python-0.5.0.dist-info/METADATA
notificationz_sdk_python-0.5.0.dist-info/RECORD
