Metadata-Version: 2.3
Name: notificationz-sdk-python
Version: 0.5.0
Requires-Dist: requests
